rpa_helpers/__init__.py
rpa_helpers/src/__init__.py
rpa_helpers/src/configuration/__init__.py
rpa_helpers/src/configuration/configuration.py
rpa_helpers/src/models/__init__.py
rpa_helpers/src/models/configs/__init__.py
rpa_helpers/src/models/configs/base.py
rpa_helpers/src/models/configs/connection.py
rpa_helpers/src/models/entities/__init__.py
rpa_helpers/src/models/entities/log.py
rpa_helpers/src/models/entities/rpa.py
rpa_helpers/src/models/repository/__init__.py
rpa_helpers/src/models/repository/repository_log.py
rpa_helpers/src/models/repository/repository_rpa.py
rpa_helpers/src/utils/__init__.py
rpa_helpers/src/utils/decorator_log.py
rpa_helpers/src/utils/send_email.py
rpa_helpers_btime-1.1.0.dist-info/METADATA
rpa_helpers_btime-1.1.0.dist-info/WHEEL
rpa_helpers_btime-1.1.0.dist-info/license.txt
rpa_helpers_btime-1.1.0.dist-info/top_level.txt
rpa_helpers_btime-1.1.0.dist-info/RECORD
