Metadata-Version: 2.1
Name: rpa-helpers-btime
Version: 1.1.0
Summary: Esse pacote irá oferecer todas as funcionalidades para auxiliar na programação de rpa.
Author: Geovanne Zanata
Author-email: geovanne.zanata@btime.com.br
Keywords: log,loggers
License-File: license.txt
Requires-Dist: colorama ==0.4.6
Requires-Dist: flake8 ==7.0.0
Requires-Dist: greenlet ==3.0.3
Requires-Dist: loguru ==0.7.2
Requires-Dist: mccabe ==0.7.0
Requires-Dist: setuptools ==69.5.1
Requires-Dist: pycodestyle ==2.11.1
Requires-Dist: pyflakes ==3.2.0
Requires-Dist: SQLAlchemy ==2.0.30
Requires-Dist: typing-extensions ==4.11.0
Requires-Dist: win32-setctime ==1.1.0
Requires-Dist: python-dotenv ==0.21.0
Requires-Dist: psycopg2
